README.rst
setup.py
pyrml/__init__.py
pyrml/module.py
pyrml/rpc.py
pyrml.egg-info/PKG-INFO
pyrml.egg-info/SOURCES.txt
pyrml.egg-info/dependency_links.txt
pyrml.egg-info/requires.txt
pyrml.egg-info/top_level.txt