Metadata-Version: 1.0
Name: pyrml
Version: 0.3.0
Summary: RainBot Module Library for Python
Home-page: http://rainbot.info/rmls#Python
Author: Rodolfo Castillo
Author-email: rcvallada@gmail.com
License: UNKNOWN
Platform: UNKNOWN
